{
 "signatures": [
  {
   "keyid": "acfcd243f8f265eaa360f8a2a0d31b793a0b194030056a36f6aca09d9a0077a0",
   "sig": "3045022100be8e472eabd319c833770a9a590e4806c3d13cc14b08e8411cd084bfa04d329602204acdf15463cc789db32977408595222f7332972897e36e1df8cac7cd1d27d27d"
  }
 ],
 "signed": {
  "_type": "snapshot",
  "expires": "2026-02-24T11:18:28Z",
  "meta": {
   "device-cli.json": {
    "version": 11
   },
   "general-service.json": {
    "version": 18
   },
   "nebula-standalone.json": {
    "version": 9
   },
   "space.json": {
    "version": 3
   },
   "targets.json": {
    "version": 33
   },
   "tunnel-integration.json": {
    "version": 33
   }
  },
  "spec_version": "1.0.31",
  "version": 88
 }
}